{
  "id": "\u4E2D\u9A6C\u7ECF\u8D38",
  "slug": "\u4E2D\u9A6C\u7ECF\u8D38",
  "canonicalUrlKey": "\u4E2D\u9A6C\u7ECF\u8D38",
  "route": "/insights/tags/\u4E2D\u9A6C\u7ECF\u8D38/",
  "title": "\u6807\u7B7E\uFF1A\u4E2D\u9A6C\u7ECF\u8D38",
  "summary": "\u6D4F\u89C8\u201C\u4E2D\u9A6C\u7ECF\u8D38\u201D\u4E0B\u7684\u5185\u5BB9\u3002",
  "body": "\u003Cul\u003E\n\u003C/ul\u003E\n",
  "language": "und",
  "type": "derived",
  "collection": "page",
  "tags": [],
  "sections": [],
  "author": null,
  "authorType": null,
  "organization": null,
  "publishedAt": "2026-07-24T00:00:00+08:00",
  "updatedAt": null,
  "expiresAt": null,
  "reviewedAt": null,
  "originalSource": null,
  "citations": [],
  "references": [],
  "syncStatus": null,
  "reviewStatus": "published",
  "credibilityScore": null,
  "qualityFlags": [],
  "entities": [],
  "relations": [],
  "media": [],
  "canonical": "https://silushangxun.com/insights/tags/\u4E2D\u9A6C\u7ECF\u8D38/"
}
